passbase/__init__.py
passbase/api_client.py
passbase/configuration.py
passbase/rest.py
passbase/api/__init__.py
passbase/api/identity_api.py
passbase/api/project_api.py
passbase/models/__init__.py
passbase/models/cursor.py
passbase/models/data_points.py
passbase/models/identity.py
passbase/models/identity_owner.py
passbase/models/identity_resource.py
passbase/models/paginated_identities.py
passbase/models/paginated_resources.py
passbase/models/project_settings.py
passbase/models/project_settings_customizations.py
passbase/models/project_settings_verification_steps.py
passbase/models/resource.py
passbase/models/resource_file.py
passbase/models/resource_files.py
passbase/models/resource_files_inner.py
passbase/models/resource_files_input.py
passbase/models/resource_files_input_inner.py
passbase/models/resource_input.py
passbase/models/resource_type.py
passbase/models/user.py
passbase/models/watchlist_response.py
test/__init__.py
test/test_cursor.py
test/test_data_points.py
test/test_identity.py
test/test_identity_api.py
test/test_identity_owner.py
test/test_identity_resource.py
test/test_paginated_identities.py
test/test_paginated_resources.py
test/test_project_api.py
test/test_project_settings.py
test/test_project_settings_customizations.py
test/test_project_settings_verification_steps.py
test/test_resource.py
test/test_resource_file.py
test/test_resource_files.py
test/test_resource_files_inner.py
test/test_resource_files_input.py
test/test_resource_files_input_inner.py
test/test_resource_input.py
test/test_resource_type.py
test/test_user.py
test/test_watchlist_response.py
passbase-1.3.0.dist-info/LICENSE
passbase-1.3.0.dist-info/METADATA
passbase-1.3.0.dist-info/WHEEL
passbase-1.3.0.dist-info/top_level.txt
passbase-1.3.0.dist-info/RECORD
