Metadata-Version: 2.1
Name: passbase
Version: 1.3.0
Summary: Verification API
Home-page: https://github.com/passbase/passbase-python
Author-email: developer@passbase.com
License: UNKNOWN
Keywords: Swagger,Verification API
Platform: UNKNOWN
Requires-Dist: urllib3 (>=1.15)
Requires-Dist: six (>=1.10)
Requires-Dist: certifi
Requires-Dist: python-dateutil
